no_vtf/__init__.py
no_vtf/__main__.py
no_vtf/_alive_progress.py
no_vtf/_click.py
no_vtf/_main.py
no_vtf/_version.py
no_vtf/main.py
no_vtf/py.typed
no_vtf/typing.py
no_vtf/core/__init__.py
no_vtf/core/pipeline.py
no_vtf/core/image/__init__.py
no_vtf/core/image/channel_separator.py
no_vtf/core/image/image.py
no_vtf/core/image/decoder/__init__.py
no_vtf/core/image/decoder/decoder.py
no_vtf/core/image/decoder/dxt.py
no_vtf/core/image/decoder/ndarray.py
no_vtf/core/image/decoder/raw.py
no_vtf/core/image/decoder/s3tc.py
no_vtf/core/image/io/__init__.py
no_vtf/core/image/io/file.py
no_vtf/core/image/io/image.py
no_vtf/core/image/io/io.py
no_vtf/core/image/io/raw.py
no_vtf/core/image/modifier/__init__.py
no_vtf/core/image/modifier/fp_precision_modifier.py
no_vtf/core/image/modifier/hdr_to_ldr_modifier.py
no_vtf/core/image/modifier/modifier.py
no_vtf/core/texture/__init__.py
no_vtf/core/texture/decoder.py
no_vtf/core/texture/extractor.py
no_vtf/core/texture/namer.py
no_vtf/core/texture/texture.py
no_vtf/core/texture/filter/__init__.py
no_vtf/core/texture/filter/face.py
no_vtf/core/texture/filter/filter.py
no_vtf/core/texture/filter/frame.py
no_vtf/core/texture/filter/mipmap.py
no_vtf/core/texture/filter/resolution.py
no_vtf/core/texture/filter/slice.py
no_vtf/core/texture/filter/texture_index.py
no_vtf/filesystem/__init__.py
no_vtf/filesystem/input_paths.py
no_vtf/filesystem/output_directories.py
no_vtf/functional/__init__.py
no_vtf/functional/deferred.py
no_vtf/task_runner/__init__.py
no_vtf/task_runner/parallel.py
no_vtf/task_runner/sequential.py
no_vtf/task_runner/task_runner.py
no_vtf/vtf/__init__.py
no_vtf/vtf/extractor.py
no_vtf/vtf/image_decoder.py
no_vtf/vtf/namer.py
no_vtf/vtf/texture.py
no_vtf/vtf/texture_decoder.py
no_vtf/vtf/generated/__init__.py
no_vtf/vtf/generated/parser.py
no_vtf-5.1.1.dist-info/licenses/LICENSES/GPL-3.0-only.txt
no_vtf-5.1.1.dist-info/METADATA
no_vtf-5.1.1.dist-info/WHEEL
no_vtf-5.1.1.dist-info/entry_points.txt
no_vtf-5.1.1.dist-info/top_level.txt
no_vtf-5.1.1.dist-info/RECORD
