Metadata-Version: 2.4
Name: no_vtf
Version: 5.1.1
Summary: Valve Texture Format Converter
Home-page: https://git.sr.ht/~b5327157/no_vtf
Author: b5327157
Author-email: b5327157@protonmail.com
License: GPL-3.0-only
Project-URL: Download, https://git.sr.ht/~b5327157/no_vtf/#application-bundle
Project-URL: Changelog, https://git.sr.ht/~b5327157/no_vtf/refs
Project-URL: Mailing list, https://lists.sr.ht/~b5327157/no_vtf
Project-URL: Ticket tracker, https://todo.sr.ht/~b5327157/no_vtf
Project-URL: Wiki, https://developer.valvesoftware.com/wiki/no_vtf
Keywords: Source Engine,VTF,Valve Texture Format
Classifier: Development Status :: 5 - Production/Stable
Classifier: Environment :: Console
Classifier: Intended Audience :: End Users/Desktop
Classifier: License :: OSI Approved :: GNU General Public License v3 (GPLv3)
Classifier: Natural Language :: English
Classifier: Operating System :: OS Independent
Classifier: Programming Language :: Python :: 3
Classifier: Programming Language :: Python :: 3 :: Only
Classifier: Programming Language :: Python :: 3.10
Classifier: Programming Language :: Python :: 3.11
Classifier: Programming Language :: Python :: 3.12
Classifier: Programming Language :: Python :: 3.13
Classifier: Topic :: Multimedia :: Graphics :: Graphics Conversion
Classifier: Typing :: Typed
Requires-Python: >=3.10
License-File: LICENSES/GPL-3.0-only.txt
Requires-Dist: alive-progress<4,>=3.1.5
Requires-Dist: click<9,>=8.1.7
Requires-Dist: click-option-group<1,>=0.5.6
Requires-Dist: imageio<3,>=2.34.0
Requires-Dist: kaitaistruct<1,>=0.10
Requires-Dist: numpy<3,>=1.26.4
Requires-Dist: pillow<12,>=10.2.0
Requires-Dist: tifffile<2025,>=2024.2.12
Requires-Dist: typing-extensions<5,>=4.9.0
Dynamic: license-file
